test.py
carsomenlp/__init__.py
carsomenlp/glossa.py
carsomenlp/matcher.py
carsomenlp/tokenizer.py
carsomenlp/translator.py
carsomenlp/utils.py
carsomenlp/wrangler.py
carsomenlp/artefacts/brand_lib.npy
carsomenlp/artefacts/brand_model.json
carsomenlp/artefacts/model_brand.json
carsomenlp/artefacts/model_lib.npy
carsomenlp/artefacts/patterns.json
carsomenlp/artefacts/tokenizer
carsomenlp-0.0.6.dist-info/LICENSE
carsomenlp-0.0.6.dist-info/METADATA
carsomenlp-0.0.6.dist-info/WHEEL
carsomenlp-0.0.6.dist-info/top_level.txt
carsomenlp-0.0.6.dist-info/RECORD
