Metadata-Version: 2.1
Name: carsomenlp
Version: 0.0.6
Summary: Carsome NLP package
Author-email: Fares Hasan <farishassan2012@gmail.com>, Ammar Syatbi <ammar.hassan@carsome.com>, Casey Cheng <casey.cheng@carsome.com>, Malik Sehgar <malik.sehgar@carsome.com>
License: Copyright (c) 2018 The Python Packaging Authority        
Project-URL: Homepage, https://github.com/pypa/sampleproject
Project-URL: Bug Tracker, https://github.com/pypa/sampleproject/issues
Classifier: Programming Language :: Python :: 3
Classifier: License :: OSI Approved :: MIT License
Classifier: Operating System :: OS Independent
Classifier: Development Status :: 3 - Alpha
Classifier: Topic :: Office/Business
Requires-Python: >=3.7
License-File: LICENSE
Requires-Dist: deep-translator (==1.8.3)
Requires-Dist: spacy (==3.4.0)
Requires-Dist: rapidfuzz (==2.2.0)
